incal/__init__.py
incal/__main__.py
incal/incremental_learner.py
incal/k_cnf_smt_learner.py
incal/learner.py
incal/lp_learner_milp.py
incal/parameter_free_learner.py
incal/example/__init__.py
incal/example/examples.py
incal/example/lp_examples.py
incal/observe/__init__.py
incal/observe/inc_logging.py
incal/observe/observe.py
incal/observe/plotting.py
incal/util/__init__.py
incal/util/sampling.py
incal/util/timeout.py
incal/violations/__init__.py
incal/violations/core.py
incal/violations/dt_selection.py
incal/violations/virtual_data.py
incal-1.0.4.dist-info/METADATA
incal-1.0.4.dist-info/WHEEL
incal-1.0.4.dist-info/entry_points.txt
incal-1.0.4.dist-info/top_level.txt
incal-1.0.4.dist-info/RECORD
