Metadata-Version: 2.1
Name: incal
Version: 1.0.4
Summary: Learning SMT(LRA) formulas
Home-page: https://github.com/smtlearning/incal
Author: Samuel Kolb
Author-email: samuel.kolb@me.com
License: MIT
Platform: UNKNOWN
Classifier: License :: OSI Approved :: MIT License
Classifier: Programming Language :: Python
Classifier: Programming Language :: Python :: 3
Requires-Python: >=3.5.0
Requires-Dist: pywmi
Requires-Dist: numpy
Requires-Dist: typing
Requires-Dist: pysmt
Requires-Dist: matplotlib
Requires-Dist: scikit-learn
